setuptools_rust_tomlgen/__init__.py
setuptools_rust_tomlgen/version.py
setuptools_rust_tomlgen-1.0.0.dist-info/LICENSE
setuptools_rust_tomlgen-1.0.0.dist-info/METADATA
setuptools_rust_tomlgen-1.0.0.dist-info/WHEEL
setuptools_rust_tomlgen-1.0.0.dist-info/entry_points.txt
setuptools_rust_tomlgen-1.0.0.dist-info/top_level.txt
setuptools_rust_tomlgen-1.0.0.dist-info/zip-safe
setuptools_rust_tomlgen-1.0.0.dist-info/RECORD
