Metadata-Version: 2.1
Name: setuptools-rust-tomlgen
Version: 1.0.0
Summary: Setuptools Rust Tomlgen extension plugin
Home-page: https://github.com/PyO3/setuptools-rust-tomlgen
Author: PyO3 Contributors
License: MIT
Keywords: distutils,setuptools,rust,tomlgen
Platform: UNKNOWN
Classifier: Topic :: Software Development :: Version Control
Classifier: License :: OSI Approved :: MIT License
Classifier: Intended Audience :: Developers
Classifier: Programming Language :: Python :: 3
Classifier: Programming Language :: Python :: 3.6
Classifier: Programming Language :: Python :: 3.7
Classifier: Programming Language :: Python :: 3.8
Classifier: Programming Language :: Python :: 3.9
Classifier: Development Status :: 5 - Production/Stable
Classifier: Operating System :: POSIX
Classifier: Operating System :: MacOS :: MacOS X
Classifier: Operating System :: Microsoft :: Windows
Requires-Python: >=3.6
License-File: LICENSE
Requires-Dist: setuptools (>=46.1)
Requires-Dist: semantic-version (>=2.6.0)
Requires-Dist: toml (>=0.9.0)
Requires-Dist: setuptools-rust (<1.0,>=0.12)
